coala-0.11.0.data/data/coala.1
coala-0.11.0.dist-info/DESCRIPTION.rst
coala-0.11.0.dist-info/METADATA
coala-0.11.0.dist-info/RECORD
coala-0.11.0.dist-info/WHEEL
coala-0.11.0.dist-info/entry_points.txt
coala-0.11.0.dist-info/metadata.json
coala-0.11.0.dist-info/top_level.txt
coalib/VERSION
coalib/__init__.py
coalib/coala.py
coalib/coala_ci.py
coalib/coala_delete_orig.py
coalib/coala_format.py
coalib/coala_json.py
coalib/coala_main.py
coalib/coala_modes.py
coalib/default_coafile
coalib/bearlib/__init__.py
coalib/bearlib/abstractions/ExternalBearWrap.py
coalib/bearlib/abstractions/Linter.py
coalib/bearlib/abstractions/SectionCreatable.py
coalib/bearlib/abstractions/__init__.py
coalib/bearlib/aspects/Metadata.py
coalib/bearlib/aspects/Redundancy.py
coalib/bearlib/aspects/Spelling.py
coalib/bearlib/aspects/__init__.py
coalib/bearlib/aspects/base.py
coalib/bearlib/aspects/collections.py
coalib/bearlib/aspects/docs.py
coalib/bearlib/aspects/meta.py
coalib/bearlib/aspects/root.py
coalib/bearlib/aspects/taste.py
coalib/bearlib/languages/Language.py
coalib/bearlib/languages/LanguageDefinition.py
coalib/bearlib/languages/__init__.py
coalib/bearlib/languages/definitions/C.py
coalib/bearlib/languages/definitions/CPP.py
coalib/bearlib/languages/definitions/CSS.py
coalib/bearlib/languages/definitions/CSharp.py
coalib/bearlib/languages/definitions/Golang.py
coalib/bearlib/languages/definitions/Java.py
coalib/bearlib/languages/definitions/JavaScript.py
coalib/bearlib/languages/definitions/Python.py
coalib/bearlib/languages/definitions/Unknown.py
coalib/bearlib/languages/definitions/Vala.py
coalib/bearlib/languages/definitions/__init__.py
coalib/bearlib/languages/documentation/DocstyleDefinition.py
coalib/bearlib/languages/documentation/DocumentationComment.py
coalib/bearlib/languages/documentation/DocumentationExtraction.py
coalib/bearlib/languages/documentation/__init__.py
coalib/bearlib/languages/documentation/default.coalang
coalib/bearlib/languages/documentation/doxygen.coalang
coalib/bearlib/languages/documentation/golang.coalang
coalib/bearlib/naming_conventions/__init__.py
coalib/bearlib/spacing/SpacingHelper.py
coalib/bearlib/spacing/__init__.py
