Metadata-Version: 2.0
Name: coala
Version: 0.11.0
Summary: Linting and Fixing Code for All Languages
Home-page: http://coala.io/
Author: Lasse Schuirmann, Fabian Neuschmidt, Mischa Krüger
Author-email: lasse.schuirmann@gmail.com, fabian@neuschmidt.de, makman@alice.de
License: AGPL-3.0
Platform: any
Classifier: Development Status :: 4 - Beta
Classifier: Environment :: Console
Classifier: Environment :: MacOS X
Classifier: Environment :: Win32 (MS Windows)
Classifier: Environment :: X11 Applications :: Gnome
Classifier: Intended Audience :: Science/Research
Classifier: Intended Audience :: Developers
Classifier: License :: OSI Approved :: GNU Affero General Public License v3 or later (AGPLv3+)
Classifier: Operating System :: OS Independent
Classifier: Programming Language :: Python :: Implementation :: CPython
Classifier: Programming Language :: Python :: 3.4
Classifier: Programming Language :: Python :: 3.5
Classifier: Programming Language :: Python :: 3 :: Only
Classifier: Topic :: Scientific/Engineering :: Information Analysis
Classifier: Topic :: Software Development :: Quality Assurance
Classifier: Topic :: Text Processing :: Linguistic
Requires-Dist: PyPrint (~=0.2.6)
Requires-Dist: Pygments (~=2.1)
Requires-Dist: appdirs (~=1.4)
Requires-Dist: coala-utils (~=0.6.2)
Requires-Dist: colorlog (~=2.7)
Requires-Dist: dependency-management (~=0.4.0)
Requires-Dist: libclang-py3 (~=3.4.0)
Requires-Dist: requests (~=2.12)
Requires-Dist: setuptools (>=17.0)
Requires-Dist: unidiff (~=0.5.2)
